poetry_workspace/__init__.py
poetry_workspace/commands/__init__.py
poetry_workspace/commands/build.py
poetry_workspace/commands/export.py
poetry_workspace/commands/loader.py
poetry_workspace/commands/workspace/__init__.py
poetry_workspace/commands/workspace/build.py
poetry_workspace/commands/workspace/list.py
poetry_workspace/commands/workspace/publish.py
poetry_workspace/commands/workspace/run.py
poetry_workspace/commands/workspace/version.py
poetry_workspace/commands/workspace/workspace.py
poetry_workspace/diff.py
poetry_workspace/errors.py
poetry_workspace/formatter.py
poetry_workspace/graph.py
poetry_workspace/plugin.py
poetry_workspace/schemas/gen_schema.py
poetry_workspace/schemas/poetry-schema.json
poetry_workspace/vcs/__init__.py
poetry_workspace/vcs/git.py
poetry_workspace/vcs/vcs.py
poetry_workspace/workspace.py
poetry_workspace_plugin2-0.5.8.dist-info/entry_points.txt
poetry_workspace_plugin2-0.5.8.dist-info/WHEEL
poetry_workspace_plugin2-0.5.8.dist-info/METADATA
poetry_workspace_plugin2-0.5.8.dist-info/RECORD
