Metadata-Version: 2.1
Name: poetry-workspace-plugin2
Version: 0.5.8
Summary: Multi project workspace plugin for Poetry
Author: Martin Liu
Author-email: martin.xs.liu@gmail.com
Requires-Python: >=3.7,<4.0
Classifier: Programming Language :: Python :: 3
Classifier: Programming Language :: Python :: 3.7
Classifier: Programming Language :: Python :: 3.8
Classifier: Programming Language :: Python :: 3.9
Classifier: Programming Language :: Python :: 3.10
Requires-Dist: poetry (>=1.2.0b3,<2.0.0)
Requires-Dist: poetry-plugin-export (>=1.0.7,<2.0.0)
